yaml_template/__init__.py
yaml_template-0.3.dist-info/LICENSE
yaml_template-0.3.dist-info/METADATA
yaml_template-0.3.dist-info/WHEEL
yaml_template-0.3.dist-info/top_level.txt
yaml_template-0.3.dist-info/RECORD
