Metadata-Version: 2.1
Name: yaml-template
Version: 0.3
Summary: 쿠버네티스처럼 YAML 파일로 이루어진 템플릿을 쉽게 템플릿의 타입에 따라 다르게 처리해주는 패키지입니다.
Home-page: https://github.com/da-huin/yaml_template
Author: JunYeong Park
Author-email: dahuin000@gmail.com
License: MIT
Download-URL: https://github.com/da-huin/yaml_template/archive/master.zip
Platform: UNKNOWN
Classifier: Programming Language :: Python :: 3
Requires-Dist: jsonschema
Requires-Dist: pyyaml
